bandcamp_librarian/.example_vars.env
bandcamp_librarian/LICENSE
bandcamp_librarian/README.rst
bandcamp_librarian/__init__.py
bandcamp_librarian/cli.py
bandcamp_librarian/docker-compose.yml
bandcamp_librarian/config/DejaVuSansCondensed-Oblique.ttf
bandcamp_librarian/config/DejaVuSansCondensed.ttf
bandcamp_librarian/config/_nocover_.jpg
bandcamp_librarian/config/beatport_classifier.sav
bandcamp_librarian/config/config.csv
bandcamp_librarian/config/csvexport.py
bandcamp_librarian/config/csvimport.py
bandcamp_librarian/config/tracks.csv
bandcamp_librarian/config/labels/labels.csv
bandcamp_librarian/config/labels/currently_scraping/label.csv
bandcamp_librarian/dataset-model-predictor/beatport_2021jan.csv
bandcamp_librarian/dataset-model-predictor/build_model.py
bandcamp_librarian/dataset-model-predictor/predict_tracks_csv.py
bandcamp_librarian/etl/Dockerfile
bandcamp_librarian/etl/etl.py
bandcamp_librarian/etl/extract_features_wav.py
bandcamp_librarian/etl/requirements.txt
bandcamp_librarian/flask/Dockerfile
bandcamp_librarian/flask/application.py
bandcamp_librarian/flask/clusterer.py
bandcamp_librarian/flask/requirements.txt
bandcamp_librarian/flask/static/css/styles.css
bandcamp_librarian/flask/static/js/script.js
bandcamp_librarian/flask/templates/admin.html
bandcamp_librarian/flask/templates/index.html
bandcamp_librarian/scraper/Dockerfile
bandcamp_librarian/scraper/requirements.txt
bandcamp_librarian/scraper/scraper.py
bandcamp_librarian-0.2.2.dist-info/AUTHORS.rst
bandcamp_librarian-0.2.2.dist-info/LICENSE
bandcamp_librarian-0.2.2.dist-info/METADATA
bandcamp_librarian-0.2.2.dist-info/WHEEL
bandcamp_librarian-0.2.2.dist-info/entry_points.txt
bandcamp_librarian-0.2.2.dist-info/top_level.txt
bandcamp_librarian-0.2.2.dist-info/RECORD
