Metadata-Version: 2.1
Name: bandcamp-librarian
Version: 0.2.2
Summary: This project detects stylistic tendencies in the Bandcamp libraries of electronic dance music labels by defining clusters based on Beatport's subgenre categories as of Jan 2021. To deploy the web interface on 0.0.0.0:8000/, enter bandcamplibrarian -on from the command line after installation. Note: the deployment requires Docker Compose pre-installed on your system.
Home-page: https://github.com/bvitos/bandcamp_librarian
Author: Botond Vitos
Author-email: boti@vitos.tv
License: MIT license
Keywords: bandcamp_librarian
Platform: UNKNOWN
Classifier: Development Status :: 4 - Beta
Classifier: Intended Audience :: Science/Research
Classifier: License :: OSI Approved :: MIT License
Classifier: Natural Language :: English
Classifier: Programming Language :: Python :: 3
Classifier: Programming Language :: Python :: 3.4
Classifier: Programming Language :: Python :: 3.5
Classifier: Programming Language :: Python :: 3.6
Classifier: Programming Language :: Python :: 3.7
License-File: LICENSE
License-File: AUTHORS.rst
Requires-Dist: numpy
Requires-Dist: pandas
Requires-Dist: sqlalchemy
Requires-Dist: psycopg2-binary
